{"informacion_general":{"identificador":"SUB-JC-2019-140460","tipo_de_subasta":"JUDICIAL CONCURSAL","fecha_de_inicio":"18-02-2020 18:00:00 CET (ISO: 2020-02-18T18:00:00+01:00)","fecha_de_conclusion":"09-03-2020 18:00:00 CET (ISO: 2020-03-09T18:00:00+01:00)","cantidad_reclamada":"0,01 €","lotes":"Sin lotes","anuncio_boe":"BOE-B-2020-6594","valor_subasta":"240.328,15 €","tasacion":"No consta","puja_minima":"Sin puja mínima","tramos_entre_pujas":"Sin tramos","importe_del_deposito":"24.032,82 €"},"autoridad_gestora":{"codigo":"1503047002","descripcion":"JUZGADO MERCANTIL 2 (Ministerio de Justicia)","direccion":"CL ENRIQUE MARIÑAS S/N S/N ; 15071 CORUÑA (A)","telefono":"881881150","fax":"881881152","correo_electronico":"mercantil2.coruna@xustiza.gal"},"bienes":{"descripcion":"URBANA.- LOCAL NÚMERO DIEZ. Vivienda NÚMERO DIEZ, perteneciente a una edificación orientado su frente a la carretera Santiago-Ourense, del proyecto de compensación de una unidad de actuación delimitada en O Martil - A Pajuela ¿ Marrozos, sita en Rúa Travesa do Sixto, nº 65-A Urbanización ¿O Martil¿, parroquia de Marrozos - A Pajuela, Santiago de Compostela (A Coruña). Referencia catastral: 0327108NH4402G0010EF.","direccion":"TRAVESIA DO SIXTO Nº65 URBANIZACION O MARTIL","codigo_postal":"15893","localidad":"SANTIAGO DE COMPOSTELA","provincia":"A Coruña","situacion_posesoria":"No consta","visitable":"No consta"},"relacionados":{"nombre":"XOSE ANTON BARREIRO PEREIRA","nif":"33292980C","direccion":"RUA 25 DE XULLO","localidad":"15705 SANTIAGO DE COMPOSTELA","provincia":"A Coruña"},"pujas":{"pujaMaxima":"124.293,21 €"}}