{"informacion_general":{"identificador":"SUB-JV-2019-121134","tipo_de_subasta":"JUDICIAL VOLUNTARIA","fecha_de_inicio":"12-03-2019 18:00:00 CET (ISO: 2019-03-12T18:00:00+01:00)","fecha_de_conclusion":"01-04-2019 22:59:00 CET (ISO: 2019-04-01T22:59:00+02:00)","cantidad_reclamada":"105.226,29 €","lotes":"Sin lotes","anuncio_boe":"BOE-B-2019-10053","valor_subasta":"105.226,29 €","tasacion":"105.226,29 €","puja_minima":"Sin puja mínima","tramos_entre_pujas":"2.104,52 €","importe_del_deposito":"5.261,31 €"},"autoridad_gestora":{"codigo":"2309241002","descripcion":"JUZGADO 1ª INST E INSTRUCC. 2 (Ministerio de Justicia)","direccion":"PZ VÁZQUEZ DE MOLINA 4 4 ; 23400 UBEDA","telefono":"953779310","fax":"953779314","correo_electronico":"mariar.jimenez.pinar@juntadeandalucia.es"},"bienes":{"descripcion":"FINCA DESTINADA A VIVIENDA EN LA CALLE AYALA, Nº 10 DE TORREPEROGIL","referencia_catastral":"23088ª004000090000XE","direccion":"CALLE AYALA, Nº 10","codigo_postal":"23320","localidad":"TORREPEROGIL","provincia":"Jaén","situacion_posesoria":"No consta","visitable":"No consta","cargas":"LAS QUE CONSTAN EN LA CERTIFICACION REGISTRAL","inscripcion_registral":"FINCA 18916 DEL REGISTRO DE LA PROPIEDAD Nº 2 DE UBEDA","informacion_adicional":"CUENTA CON UNA SUPERFICIE DE 116,80 METROS CUADRADOS. FINCA REGISTRAL 18916 DEL R.P. Nº 2 DE UBEDA"},"relacionados":{},"pujas":{"pujaMaxima":"50.508,48 €"}}