{"informacion_general":{"identificador":"SUB-JA-2016-34615","tipo_de_subasta":"JUDICIAL EN VIA DE APREMIO","fecha_de_inicio":"05-09-2017 18:00:00 CET (ISO: 2017-09-05T18:00:00+02:00)","fecha_de_conclusion":"25-09-2017 18:00:00 CET (ISO: 2017-09-25T18:00:00+02:00)","cantidad_reclamada":"204.500,61 €","lotes":"Sin lotes","anuncio_boe":"BOE-B-2017-49954","valor_subasta":"336.566,78 €","tasacion":"No consta","puja_minima":"Sin puja mínima","tramos_entre_pujas":"Sin tramos","importe_del_deposito":"16.828,34 €"},"autoridad_gestora":{"codigo":"0818742004","descripcion":"JUZGADO 1ª INSTANCIA 4 (Ministerio de Justicia)","direccion":"AV FRANCESC MACIA 36 36 ; 08208 SABADELL","telefono":"937232119","fax":"937232119","correo_electronico":"-"},"bienes":{"descripcion":"Finca nº 4206, inscrita en el Registro de la Propiedad nº 1 de Sabadell, Tomo 1395, Libro 105, folio 53, Sección de Castellar del Vallès","direccion":"calle valles 14","codigo_postal":"08204","localidad":"castellar del valles","provincia":"Barcelona","situacion_posesoria":"No consta","visitable":"No consta"},"relacionados":{"nombre":"Banco Bilbao Vizcaya Argentaria SA","nif":"A48265169","direccion":"PLAZA SAN NICOLAS 4","localidad":"48005 BILBAO","provincia":"Vizcaya"},"pujas":{"pujaMaxima":"213.255,55 €"}}