{"informacion_general":{"identificador":"SUB-JA-2016-12382","tipo_de_subasta":"JUDICIAL EN VIA DE APREMIO","fecha_de_inicio":"21-05-2016 00:00:00 CET (ISO: 2016-05-21T00:00:00+02:00)","fecha_de_conclusion":"10-06-2016 00:56:49 CET (ISO: 2016-06-10T00:56:49+02:00)","cantidad_reclamada":"0,01 €","lotes":"Sin lotes","anuncio_boe":"BOE-B-2016-20920","valor_subasta":"300.200,00 €","tasacion":"No consta","puja_minima":"Sin puja mínima","tramos_entre_pujas":"Sin tramos","importe_del_deposito":"15.010,00 €"},"autoridad_gestora":{"codigo":"2807942031","descripcion":"JUZGADO 1ª INSTANCIA 31 (Ministerio de Justicia)","direccion":"CL CAPITAN HAYA 66 66 ; 28020 MADRID","telefono":"914932843","fax":"914932844","correo_electronico":"juzpriminstancia031madrid@madrid.org"},"bienes":{"descripcion":"INFANTA MERCEDES 62-LOCAL 9 EN PLANTA 4º MADRID","direccion":"INFANTA MERCEDES 62 LOCAL 9 PLANTA 4º","codigo_postal":"28020","localidad":"MADRID","provincia":"Madrid","situacion_posesoria":"No consta","visitable":"No consta"},"relacionados":{"nombre":"BANKIA SA","nif":"A14010342","direccion":"PINTOR SOROLLA 8","localidad":"46002 VALENCIA","provincia":"Valencia"},"pujas":{"pujaMaxima":"115.000,00 €"}}