{"informacion_general":{"identificador":"SUB-JA-2017-73221","tipo_de_subasta":"JUDICIAL EN VIA DE APREMIO","fecha_de_inicio":"19-09-2017 18:00:00 CET (ISO: 2017-09-19T18:00:00+02:00)","fecha_de_conclusion":"09-10-2017 18:00:00 CET (ISO: 2017-10-09T18:00:00+02:00)","cantidad_reclamada":"123.316,89 €","lotes":"Sin lotes","anuncio_boe":"BOE-B-2017-52684","valor_subasta":"241.828,05 €","tasacion":"No consta","puja_minima":"Sin puja mínima","tramos_entre_pujas":"Sin tramos","importe_del_deposito":"12.091,40 €"},"autoridad_gestora":{"codigo":"4508141002","descripcion":"JUZGADO 1ª INST E INSTRUCC. 2 (Ministerio de Justicia)","direccion":"CL DE LA CRUZ 7 7 ; 45200 ILLESCAS","telefono":"925532251","fax":"925512350","correo_electronico":"-"},"bienes":{"descripcion":"DESCRIPCION: Vivienda unifamiliar o chalet nº 44 fase 4 denominado comercialmente ATENAS-A","referencia_catastral":"1293709VK4319S0001GF","direccion":"CALLE PRINCIPE DE ASTURIAS 99","codigo_postal":"45223","localidad":"SESEÑA","provincia":"Toledo","situacion_posesoria":"No consta","visitable":"No consta"},"relacionados":{"nombre":"BANCO DE CASTILLA LA MANCHA SA","nif":"A15011489","direccion":"PARQUE SAN JULIAN N º 20","localidad":"16001 CUANCA","provincia":"Cuenca"},"pujas":{"pujaMaxima":"158.389,00 €"}}