{"informacion_general":{"identificador":"SUB-JA-2018-88936","tipo_de_subasta":"JUDICIAL EN VIA DE APREMIO","fecha_de_inicio":"20-02-2018 18:00:00 CET (ISO: 2018-02-20T18:00:00+01:00)","fecha_de_conclusion":"12-03-2018 18:46:14 CET (ISO: 2018-03-12T18:46:14+01:00)","cantidad_reclamada":"55.978,97 €","lotes":"Sin lotes","anuncio_boe":"BOE-B-2018-9363","valor_subasta":"149.700,00 €","tasacion":"No consta","puja_minima":"Sin puja mínima","tramos_entre_pujas":"Sin tramos","importe_del_deposito":"7.485,00 €"},"autoridad_gestora":{"codigo":"2807942100","descripcion":"JUZGADO 1ª INSTANCIA 100 (Ministerio de Justicia)","direccion":"CL PRINCESA 3 3 ; 28008 MADRID","telefono":"914437912","fax":"-","correo_electronico":"juzpriminstancia100madrid@madrid.org"},"bienes":{"descripcion":"CALLE SOR MARIA DE AGREDA, 47- BAJO 2 DE MADRID","direccion":"CALLE SOR MARIA DE AGREDA, 47 - BAJO 2","codigo_postal":"28017","localidad":"MADRID","provincia":"Madrid","situacion_posesoria":"No consta","visitable":"No consta"},"relacionados":{"nombre":"CAIXABANK, S.A.","nif":"A08663619","direccion":"AVDA DIAGONAL, 621","localidad":"08028 BARCELONA","provincia":"Barcelona"},"pujas":{"pujaMaxima":"78.300,00 €"}}