{"informacion_general":{"identificador":"SUB-JA-2019-137678","tipo_de_subasta":"JUDICIAL EN VIA DE APREMIO","fecha_de_inicio":"21-11-2019 18:00:00 CET (ISO: 2019-11-21T18:00:00+01:00)","fecha_de_conclusion":"11-12-2019 19:56:11 CET (ISO: 2019-12-11T19:56:11+01:00)","cantidad_reclamada":"115.882,04 €","lotes":"Sin lotes","anuncio_boe":"BOE-B-2019-49336","valor_subasta":"231.040,00 €","tasacion":"No consta","puja_minima":"Sin puja mínima","tramos_entre_pujas":"4.620,80 €","importe_del_deposito":"11.552,00 €"},"autoridad_gestora":{"codigo":"3800642002","descripcion":"JUZGADO 1ª INSTANCIA 2 (Ministerio de Justicia)","direccion":"AV CHAYOFITA S/N S/N ; 38650 PLAYA DE LOS CRISTIANOS","telefono":"922747375","fax":"922787861","correo_electronico":"instancia2.aron@justiciaencanarias.org"},"bienes":{"descripcion":"Urbana: nº setenta, piso en planta segunda, de la casa letra D, con una superficie de 85,76 m2, en Urb. Cristimar, trastero con una superficie de 11,45 m2 y una plaza de garaje con una superficie de 26,96 m2","idufir":"38016000265465","referencia_catastral":"no consta","direccion":"Urb. Cristimar, Bl. D, 2º, 3º, Los Cristianos, Arona","codigo_postal":"38650","localidad":"Arona","provincia":"Santa Cruz de Tenerife","situacion_posesoria":"No consta","visitable":"No consta"},"relacionados":{"nombre":"BANCO DE SABADELL","nif":"A08000143","direccion":"PZ DE CATALU#A 1","localidad":"08201 SABADELL","provincia":"Barcelona","pais":"España"},"pujas":{"pujaMaxima":"152.486,40 €"}}