{"informacion_general":{"identificador":"SUB-NE-2017-275534","tipo_de_subasta":"NOTARIAL EN VENTA EXTRAJUDICIAL","fecha_de_inicio":"20-06-2017 18:00:00 CET (ISO: 2017-06-20T18:00:00+02:00)","fecha_de_conclusion":"10-07-2017 18:00:00 CET (ISO: 2017-07-10T18:00:00+02:00)","cantidad_reclamada":"83.982,12 €","lotes":"Sin lotes","anuncio_boe":"BOE-B-2017-37961","valor_subasta":"100.621,37 €","tasacion":"100.621,37 €","puja_minima":"Sin puja mínima","tramos_entre_pujas":"Sin tramos","importe_del_deposito":"5.031,07 €"},"autoridad_gestora":{"codigo":"3331399","descripcion":"Gabriel Díaz Sevillano (ANCERT)","direccion":"Mallent i Meri, 32, 1º, 2ª ; 46980 Paterna","telefono":"961.828.070","fax":"-","correo_electronico":"gdiaz@correonotarial.org"},"bienes":{"descripcion":"SUBASTA POR TRAMITACIÓN DE VENTA EXTRAJUDICIAL","referencia_catastral":"9066101YJ1796N0024BS","direccion":"CALLE LES ONES, 5 BAJO","codigo_postal":"46980","localidad":"Paterna","provincia":"Valencia","vivienda_habitual":"No","situacion_posesoria":"Sin ocupantes","visitable":"Sí","cargas":"ANOTACIÓN PREVENTIVA DE EMBARGO A FAVOR DE BBVA","inscripcion_registral":"FINCA 69662 DE PATERNA","titulo_juridico":"HIPOTECA"},"relacionados":{},"pujas":{"pujaMaxima":null}}