{"informacion_general":{"identificador":"SUB-JA-2019-135859","tipo_de_subasta":"JUDICIAL EN VIA DE APREMIO","fecha_de_inicio":"15-10-2019 18:00:00 CET (ISO: 2019-10-15T18:00:00+02:00)","fecha_de_conclusion":"04-11-2019 19:09:46 CET (ISO: 2019-11-04T19:09:46+01:00)","cantidad_reclamada":"32.601,61 €","lotes":"Sin lotes","anuncio_boe":"BOE-B-2019-42874","valor_subasta":"21.516,72 €","tasacion":"No consta","puja_minima":"Sin puja mínima","tramos_entre_pujas":"Sin tramos","importe_del_deposito":"1.075,83 €"},"autoridad_gestora":{"codigo":"2512042004","descripcion":"JUZGADO 1ª INSTANCIA 4 (Ministerio de Justicia)","direccion":"CL CANYERET 8 8 ; 25007 LLEIDA","telefono":"973700133","fax":"973700263","correo_electronico":"nstancia4.lleida@xij.gencat.cat"},"bienes":{"descripcion":"PLAZA PARKING EN LLEIDA","idufir":"25010000786964","direccion":"C. RONDA SAN MARTI 24 26 28 30","codigo_postal":"25006","localidad":"LLEIDA","provincia":"Lérida","vivienda_habitual":"No","situacion_posesoria":"No consta","visitable":"No consta","cargas":"CONSTAN EN CERTIFICACIÓN CARGAS","inscripcion_registral":"finca 92.607, con código registral único 25010000787275, del término de LLEIDA, obrante al folio 109 y siguientes del tomo 2488 del Archivo, libro 1635, segon registro."},"relacionados":{"nombre":"CAIXABANK SA","nif":"A08663619","direccion":"AV. DIAGONAL 621","localidad":"08028 BARCELONA","provincia":"Barcelona","pais":"España"},"pujas":{"pujaMaxima":"11.862,00 €"}}