{"informacion_general":{"identificador":"SUB-JA-2019-128936","tipo_de_subasta":"JUDICIAL EN VIA DE APREMIO","fecha_de_inicio":"14-06-2019 18:00:00 CET (ISO: 2019-06-14T18:00:00+02:00)","fecha_de_conclusion":"04-07-2019 18:00:00 CET (ISO: 2019-07-04T18:00:00+02:00)","cantidad_reclamada":"107.468,93 €","lotes":"Sin lotes","anuncio_boe":"BOE-B-2019-26000","valor_subasta":"107.833,81 €","tasacion":"No consta","puja_minima":"Sin puja mínima","tramos_entre_pujas":"2.156,67 €","importe_del_deposito":"5.391,69 €"},"autoridad_gestora":{"codigo":"4508141002","descripcion":"JUZGADO 1ª INST E INSTRUCC. 2 (Ministerio de Justicia)","direccion":"CL HERNAN CORTES 7 7 ; 45200 ILLESCAS","telefono":"925532251","fax":"925513508","correo_electronico":"MIXTO2.ILLESCAS@JUSTICIA.ES"},"bienes":{"descripcion":"Finca registral nº 5097 inscrita en el Tomo 1477, libro 282, folio 149 del Registro de la propiedad nº 1 de Illescas","direccion":"CALLE TOLEDO 17, PORTAL 5, BAJO-B","codigo_postal":"45212","localidad":"LOMINCHAR","provincia":"Toledo","vivienda_habitual":"No","situacion_posesoria":"No consta","visitable":"No consta"},"relacionados":{},"pujas":{"pujaMaxima":"56.073,42 €"}}