{"informacion_general":{"identificador":"SUB-NE-2018-345576","tipo_de_subasta":"NOTARIAL EN VENTA EXTRAJUDICIAL","fecha_de_inicio":"01-02-2018 18:00:00 CET (ISO: 2018-02-01T18:00:00+01:00)","fecha_de_conclusion":"21-02-2018 18:00:00 CET (ISO: 2018-02-21T18:00:00+01:00)","cantidad_reclamada":"161.629,75 €","lotes":"Sin lotes","anuncio_boe":"BOE-B-2018-5448","valor_subasta":"234.746,00 €","tasacion":"234.746,00 €","puja_minima":"Sin puja mínima","tramos_entre_pujas":"Sin tramos","importe_del_deposito":"11.737,30 €"},"autoridad_gestora":{"codigo":"7501535","descripcion":"José Javier Castiella Rodríguez (ANCERT)","direccion":"C/ Libreros, 14 - 2º ; 28801 Alcalá de Henares","telefono":"918.772.090","fax":"-","correo_electronico":"jjcastiella@correonotarial.org"},"bienes":{"descripcion":"PISO 4 B, EN CALLE RIO ALAGON, 11","idufir":"28070000149579","referencia_catastral":"9303601VK6890S0020JQ","direccion":"CALLE RIO ALAGON, 11, 4ºB","codigo_postal":"28803","localidad":"Alcalá de Henares","provincia":"Madrid","vivienda_habitual":"Sí","situacion_posesoria":"Ocupantes con derecho de permanencia","visitable":"No","cargas":"INSC. 7, HIPOTECA A FAVOR DE BBVA, IMPORTE 187.000€; HIPOTECA A FAVOR DE BBVA, IMPORTE 25.600 € Y MA","inscripcion_registral":"FINCA 9175, FOLIO 178, TOMO 3508 REGISTRO 5 DE ALC","titulo_juridico":"HIPOTECA"},"relacionados":{},"pujas":{"pujaMaxima":null}}