{"informacion_general":{"identificador":"SUB-JA-2019-121350","tipo_de_subasta":"JUDICIAL EN VIA DE APREMIO","fecha_de_inicio":"02-04-2019 18:00:00 CET (ISO: 2019-04-02T18:00:00+02:00)","fecha_de_conclusion":"22-04-2019 18:00:00 CET (ISO: 2019-04-22T18:00:00+02:00)","cantidad_reclamada":"103.134,13 €","lotes":"Sin lotes","anuncio_boe":"BOE-B-2019-13534","valor_subasta":"270.501,83 €","tasacion":"No consta","puja_minima":"Sin puja mínima","tramos_entre_pujas":"5.410,03 €","importe_del_deposito":"13.525,09 €"},"autoridad_gestora":{"codigo":"0401342001","descripcion":"JUZGADO 1ª INSTANCIA 1 (Ministerio de Justicia)","direccion":"CR DE RONDA 120 120 ; 04006 ALMERIA","telefono":"950809073","fax":"950204214","correo_electronico":"jinstancia.1.almeria.jus@juntadeandalucia.es"},"bienes":{"descripcion":"ENTIDAD SEIS, URBANA, NAVE INDUSTRIAL, señalada con el número B-2, en el bloque B de un complejo inmobiliario localizado en Níjar, barriada de La Venta del Pobre, paraje Cañada de Filtro. Compuesto de una sola planta más un patio a su frente desde la prolongación ideal de su fachada Sur hasta la vía pública. Extensión: cuatrocientos doce metros con noventa y dos decímetros cuadrados construidos más el patio de setenta y tres metros con cincuenta decímetros cuadrados. Linda: Norte, entidad ocho, nave B-4; Sur, vía pública a través de su propio patio; Este, entidad siete, nave B-3; y Oeste, entidad cinco, nave B-1. CUOTA: nueve enteros por ciento.","direccion":"PARAJE CAÑADA DEL FILTRO, BARRIADA DE LA VENTA DEL POBRE, NIJAR","codigo_postal":"04114","localidad":"NIJAR","provincia":"Almería","vivienda_habitual":"No","situacion_posesoria":"No consta","visitable":"No consta"},"relacionados":{"nombre":"LC ASSET 1 S.A.R.L.,","nif":"N0038834H","direccion":"No consta","localidad":"No consta No consta","provincia":"-","pais":"XG"},"pujas":{"pujaMaxima":"129.840,72 €"}}