{"informacion_general":{"identificador":"SUB-JA-2019-119817","tipo_de_subasta":"JUDICIAL EN VIA DE APREMIO","fecha_de_inicio":"05-03-2019 18:00:00 CET (ISO: 2019-03-05T18:00:00+01:00)","fecha_de_conclusion":"25-03-2019 19:12:08 CET (ISO: 2019-03-25T19:12:08+01:00)","cantidad_reclamada":"407.573,21 €","lotes":"2","forma_adjudicacion":"Separada para cada lote","anuncio_boe":"BOE-B-2019-8666","valor_subasta":"Ver valor de subasta en cada lote (los lotes se subastan de forma independiente)","tasacion":"Ver valor de tasación en cada lote (los lotes se subastan de forma independiente)","puja_minima":"Ver puja mínima de cada lote (adjudicación independiente)","tramos_entre_pujas":"Ver tramos de cada lote (adjudicación independiente)","importe_del_deposito":"Ver importe de consignación de cada lote (adjudicación independiente)"},"autoridad_gestora":{"codigo":"3200941002","descripcion":"JUZGADO 1ª INST E INSTRUCC. 2 (Ministerio de Justicia)","direccion":"CL EULOGIO FERNANDEZ S/N 1 ; 32300 BARCO DE VALDEORRAS (O)","telefono":"988687484","fax":"988687488","correo_electronico":"mixto2.obarco@xustiza.gal"},"lotes":{"1":{"valor_subasta":"268.110,00 €","valor_de_tasacion":"268.110,00 €","importe_del_deposito":"13.405,50 €","puja_minima":"Sin puja mínima","tramos_entre_pujas":"5.362,20 €","descripcion":"CASA UNIFAMILIAR CON SOTANO PLANTA BAJA Y PRIMERA","direccion":"PARCELA 4 , AREA DE REPARTO 8, SECTOR SUR 8 PLAN GENERAL DE O BARCO","codigo_postal":"32300","localidad":"BARCO DE VALDEORRAS","provincia":"Orense","vivienda_habitual":"No","situacion_posesoria":"No consta (ESCRITURA PUBLICA)","visitable":"No","inscripcion_registral":"TOMO 588, LIBRO 196, FOLIO 94 FINCA 22166, REGISTRO DE O BARCO DE VALDEORRAS","informacion_adicional":"CASA CONSTRUIDA SOBRE PARCELA 4 DE AREA DE REPARTO 8, SECTOR SUR 8 DEL PLAN GENERAL DE O BARCO DE VALDEORRAS"},"2":{"valor_subasta":"268.110,00 €","valor_de_tasacion":"268.110,00 €","importe_del_deposito":"13.405,50 €","puja_minima":"Sin puja mínima","tramos_entre_pujas":"5.362,20 €","descripcion":"CASA VIVIENDA UNIFAMILIAR COMPUEST DE SOTANO , BAJO Y PRIMERA PLANTA","direccion":"PARCELA 5 SECTOR SUR 8","codigo_postal":"32300","localidad":"O BARCO DE VALDEORRAS","provincia":"Orense","vivienda_habitual":"No","situacion_posesoria":"No consta (ESCRITURA PUBLICA)","visitable":"No","inscripcion_registral":"TOMO 588, LIBRO 196 FOLIO 96, FINCA 22167, REGISRO DE O BARCO DE VALDEORRAS","informacion_adicional":"PARCELA 5 AREA DE REPARTO 8, SECTOR SUR -8 DEL PLAN GENERAL DE O BARCO"}},"relacionados":{"nombre":"SOCIEDAD DE GESTION DE ACTIVOS PROCEDENTES DE REES","nif":"A86602158","direccion":"PASEO DE LA CASTELLANA 89","localidad":"28046 MADRID","provincia":"Madrid","pais":"España"},"pujas":{"1":"Sin puja","2":"80.433,00 €"}}