{"informacion_general":{"identificador":"SUB-JA-2019-123362","tipo_de_subasta":"JUDICIAL EN VIA DE APREMIO","fecha_de_inicio":"09-04-2019 18:00:00 CET (ISO: 2019-04-09T18:00:00+02:00)","fecha_de_conclusion":"29-04-2019 18:00:00 CET (ISO: 2019-04-29T18:00:00+02:00)","cantidad_reclamada":"99.816,43 €","lotes":"Sin lotes","anuncio_boe":"BOE-B-2019-14993","valor_subasta":"225.047,05 €","tasacion":"No consta","puja_minima":"Sin puja mínima","tramos_entre_pujas":"4.500,94 €","importe_del_deposito":"11.252,35 €"},"autoridad_gestora":{"codigo":"4517341004","descripcion":"JUZGADO 1ª INST E INSTRUCC. 4 (Ministerio de Justicia)","direccion":"AV DEL PILAR S/N S/N ; 45500 TORRIJOS","telefono":"925764970","fax":"925764961","correo_electronico":"mixto4.torrijos@justicia.es"},"bienes":{"descripcion":"URBANA VIVIENDA SEÑALADA CON LA LETRA B EN PLANTA SEGUNDA DEL EDIFICIO EN FUENSALIDA","direccion":"CALLE MADRID","codigo_postal":"45510","localidad":"FUENSALIDA","provincia":"Toledo","vivienda_habitual":"No","situacion_posesoria":"No consta","visitable":"No consta"},"relacionados":{},"pujas":{"pujaMaxima":"67.514,10 €"}}