{"informacion_general":{"identificador":"SUB-JA-2017-70215","tipo_de_subasta":"JUDICIAL EN VIA DE APREMIO","fecha_de_inicio":"25-07-2017 18:00:00 CET (ISO: 2017-07-25T18:00:00+02:00)","fecha_de_conclusion":"15-08-2017 01:46:56 CET (ISO: 2017-08-15T01:46:56+02:00)","cantidad_reclamada":"52.163,18 €","lotes":"Sin lotes","anuncio_boe":"BOE-B-2017-44883","valor_subasta":"298.389,00 €","tasacion":"No consta","puja_minima":"Sin puja mínima","tramos_entre_pujas":"Sin tramos","importe_del_deposito":"14.919,45 €"},"autoridad_gestora":{"codigo":"0306542005","descripcion":"JUZGADO 1ª INSTANCIA 5 (Ministerio de Justicia)","direccion":"PZ REYES CATOLICOS S/N S/N ; 03201 ELCHE","telefono":"966917341","fax":"966917350","correo_electronico":"-"},"bienes":{"descripcion":"HORT DEL BORREGUET, 16-2º PUERTA 3 DE ELCHE","referencia_catastral":"1875102YH0317F0025UW","direccion":"C/ HORT DEL BORREGUET, 16-2º PUERTA 3","codigo_postal":"03203","localidad":"ELCHE","provincia":"Alicante","situacion_posesoria":"No consta","visitable":"No consta"},"relacionados":{"nombre":"BANCO DE VALENCIA","nif":"A46002036","direccion":"C/ PINTOR SOROLLA, 2-4 VALENCIA","localidad":"46002 VALENCIA","provincia":"Valencia"},"pujas":{"pujaMaxima":"87.000,01 €"}}