{"informacion_general":{"identificador":"SUB-AT-2020-19R0886001518","tipo_de_subasta":"AGENCIA TRIBUTARIA","fecha_de_inicio":"28-01-2020 18:00:00 CET (ISO: 2020-01-28T18:00:00+01:00)","fecha_de_conclusion":"17-02-2020 18:18:49 CET (ISO: 2020-02-17T18:18:49+01:00)","lotes":"Sin lotes","anuncio_boe":"BOE-B-2020-3161","valor_subasta":"120.227,43 €","tasacion":"120.227,43 €","puja_minima":"Sin puja mínima","tramos_entre_pujas":"2.000,00 €","importe_del_deposito":"6.011,37 €"},"autoridad_gestora":{"codigo":"R08860","descripcion":"U.R. SUBASTAS CATALUÑA (AEAT)","direccion":"PZ DOCTOR LETAMENDI 13-22 ; 08071 BARCELONA","telefono":"932911200","fax":"934518930","correo_electronico":"subastas.cataluna@correo.aeat.es"},"bienes":{"descripcion":"ENTIDAD NUMERO UNO. LOCAL PARKING, EN FASE DE CONSTRUCCIÓN, EN PLANTA SÓTANO DEL EDIFICIO \"LA CRUILLA\", L'ESCALA, C/GIRONA,76. SE COMPONE DE NAVE Y SERVICIOS, INTEGRANTE DE 13 PLAZAS DE APARCAMIENTO Y 13 CUARTOS TRASTEROS.UNA SUPERFICIE DE 350,10 M2. NO TIENE ACCESO A TRAVÉS DEL ASCENSOR DEL EDIFICIO,ÚNICO ACCESO ES MEDIANTE UN PASO PEATONAL EN LA PUERTA PARA VEHÍCULOS. LINDA: AL FRENTE C/GIRONA CON LOCAL COMERCIAL Y JARDÍN DE USO PRIVATIVOS DE DICHO LOCAL. DERECHA ENTRANDO: CON JOSE LOPEZ Y FRANCISCA VACAS GIBERT. IZQU: ZONA COMUN DE ACCESO A LA CARRETERA DE VILADEMAT A TORROELLA DE MONTGRÍ,AL FONDO CON LA FINCA DE SEÑORES FIGUERAS SU CUOTA ES DE 13,60%.","idufir":"17010000079654","referencia_catastral":"0729209EG1602N0001AT","direccion":"CL GIRONA 76 -1 1","codigo_postal":"17130","localidad":"L'ESCALA","provincia":"Gerona","situacion_posesoria":"No consta","visitable":"No consta","cargas":"0,00 €","inscripcion_registral":"BIEN INSCRITO EN REGISTRO DE L'ESCALA TOMO: 2810 , FOLIO: 131 , LIBRO: 476. FINCA: 12223 , INSCRIPCIÓN: 6","titulo_juridico":"PLENO DOMINIO"},"relacionados":{},"pujas":{"pujaMaxima":"28.000,00 €"}}