{"informacion_general":{"identificador":"SUB-NE-2017-335544","tipo_de_subasta":"NOTARIAL EN VENTA EXTRAJUDICIAL","fecha_de_inicio":"31-10-2017 18:00:00 CET (ISO: 2017-10-31T18:00:00+01:00)","fecha_de_conclusion":"20-11-2017 18:00:00 CET (ISO: 2017-11-20T18:00:00+01:00)","cantidad_reclamada":"287.757,75 €","lotes":"Sin lotes","anuncio_boe":"BOE-B-2017-63181","valor_subasta":"275.848,00 €","tasacion":"275.848,00 €","puja_minima":"Sin puja mínima","tramos_entre_pujas":"Sin tramos","importe_del_deposito":"13.792,40 €"},"autoridad_gestora":{"codigo":"0908199","descripcion":"Ana María Vázquez Vázquez (ANCERT)","direccion":"Dante Alighieri, 98, pral. ; 08032 Barcelona","telefono":"934.074.319","fax":"-","correo_electronico":"amvazquez@correonotarial.org"},"bienes":{"descripcion":"PISO DESTINADO A VIVIENDA","referencia_catastral":"7510709DF2871B0003FL","direccion":"CALLE SANTS, NUMERO 172, PISO ENTRESULEO, PUERTA 1","codigo_postal":"08028","localidad":"Barcelona","provincia":"Barcelona","vivienda_habitual":"Sí","situacion_posesoria":"Sin ocupantes","visitable":"No","cargas":"VIVIENDA DE RENTA LIMITADA CADUCADA, HIPOTECA BBVA, EMBARGO HACIENDA, EMBARGO SEGURIDAD SOCIAL","inscripcion_registral":"14 BN- T3341- L 583- F 30- NUMERO 17699","titulo_juridico":"COMPRAVENTA","informacion_adicional":"LA ACTUAL PROPIEDAD NO RESIDE EN EL INMUEBLE"},"relacionados":{},"pujas":{"pujaMaxima":null}}