{"informacion_general":{"identificador":"SUB-JA-2019-128480","tipo_de_subasta":"JUDICIAL EN VIA DE APREMIO","fecha_de_inicio":"18-06-2019 18:00:00 CET (ISO: 2019-06-18T18:00:00+02:00)","fecha_de_conclusion":"08-07-2019 19:49:35 CET (ISO: 2019-07-08T19:49:35+02:00)","cantidad_reclamada":"174.618,95 €","lotes":"Sin lotes","anuncio_boe":"BOE-B-2019-26658","valor_subasta":"321.216,00 €","tasacion":"No consta","puja_minima":"Sin puja mínima","tramos_entre_pujas":"6.424,32 €","importe_del_deposito":"16.060,80 €"},"autoridad_gestora":{"codigo":"0702642002","descripcion":"JUZGADO 1ª INSTANCIA 2 (Ministerio de Justicia)","direccion":"AV SAN CRISTOFORO S/N 4 ; 07800 IBIZA","telefono":"971315518","fax":"971190278","correo_electronico":"instancia2.ibiza@justicia.es"},"bienes":{"descripcion":"Finca registral número 26.480 inscrita en el Registro de la Propiedad nº 3 de Ibiza al tomo 1715, libro 632, folio 100. Descripción: VIVIENDA PISO en Nuestra Señora de Jesús, de la planta piso primero, puerta número uno, señalada comercialmente como escalera uno, piso primero, puerta número cinco, de sesenta y dos metros, noventa decímetros cuadrados (62,90 m2) de superficie, con terrazas cubiertas, distribuida en varias y habitaciones y dependencias. Linda: Frente entrando o Norte, pasillo distribuidor y hueco de la escalera, vuelo del solar y parte con la entidad registral número cuatro; derecha entrando u Oeste, entidad registral número siete; izquierda entrando o Este, parte con entidad registral número cuatro y parte con vuelo del solar; fondo o Sur, con vuelo del solar; techo, entidad registral número cinco; pavimento, entidad registral número uno.","referencia_catastral":"6397021CD6069N0013BQ","direccion":"Cap Martinet nº 165, Ed. Ses Torres, Esc. 1, 1º 5ª","codigo_postal":"07819","localidad":"Ntra. Sra. Jesús, Santa Eulalia del Río","provincia":"Baleares","situacion_posesoria":"No consta","visitable":"No consta"},"relacionados":{"nombre":"UNIÓN DE CRÉDITOS INMOBILIARIOS, S.A.","nif":"A39025515","direccion":"C/ RETAMA, 3","localidad":"28045 MADRID","provincia":"Madrid","pais":"España"},"pujas":{"pujaMaxima":"199.153,92 €"}}