{"informacion_general":{"identificador":"SUB-AT-2019-19R0886001363","tipo_de_subasta":"AGENCIA TRIBUTARIA","fecha_de_inicio":"03-12-2019 18:00:00 CET (ISO: 2019-12-03T18:00:00+01:00)","fecha_de_conclusion":"23-12-2019 20:17:11 CET (ISO: 2019-12-23T20:17:11+01:00)","lotes":"Sin lotes","anuncio_boe":"BOE-B-2019-51888","valor_subasta":"150.344,39 €","tasacion":"197.301,18 €","puja_minima":"Sin puja mínima","tramos_entre_pujas":"2.000,00 €","importe_del_deposito":"7.517,21 €"},"autoridad_gestora":{"codigo":"R08860","descripcion":"U.R. SUBASTAS CATALUÑA (AEAT)","direccion":"PZ DOCTOR LETAMENDI 13-22 ; 08071 BARCELONA","telefono":"932911211","fax":"934518930","correo_electronico":"subastas.cataluna@correo.aeat.es"},"bienes":{"descripcion":"CASA Y TERRENO ADJUNTO, SITA EN EL TÉRMINO MUNICIPAL DE CASTELLO D ´AMPURIAS NUMERO 109 DEL SECTOR MONTSENY, URB EMPURIABRAVA, DE SUPERFICIE EN JUNTO 230,72 M2, DE LOS QUE LA CASA DE PLANTA BAJA, DESTINADA A VIVIENDA FAMILIAR, OCUPA UNA SUPERFICIE APROXIMADA DE 75 M2, CONSTA DE RECIBO, COMEDOR-ESTAR-COCINA, BAÑO Y DOS HABITACIONES. LINDANTE NORESTE, FINCA SITUADA PASAJE MONSENY, 94, PROPIEDAD DE HORST HEESE; NOROESTE FINCA SITUADA EN PASAJE MONTSENY, 110, PROPIEDAD DE DOLORES BERMÚDEZ AGUILAR; SURESTE, PASAJE MONSENY, 108, PROPIEDAD DE MARCEL MOLLARD Y EN PARTE CALLE MONSENY, 109-A, PROPIEDAD DE ALEJANDRO CARLOS OTERO OTÓN.","idufir":"17020000117829","referencia_catastral":"9071323EG0797S0001RS","direccion":"UR AMPURIABRAVA 0","codigo_postal":"17486","localidad":"CASTELLO D'EMPURIES","provincia":"Gerona","situacion_posesoria":"No consta","visitable":"No consta","cargas":"46.956,79 €","inscripcion_registral":"BIEN INSCRITO EN REGISTRO NÚM. 2 DE ROSES TOMO: 2617 , FOLIO: 148 , LIBRO: 253. FINCA: 9240 , INSCRIPCIÓN: 10","titulo_juridico":"PLENO DOMINIO"},"relacionados":{},"pujas":{"pujaMaxima":"56.000,00 €"}}