{"informacion_general":{"identificador":"SUB-JA-2019-118128","tipo_de_subasta":"JUDICIAL EN VIA DE APREMIO","fecha_de_inicio":"12-02-2019 18:00:00 CET (ISO: 2019-02-12T18:00:00+01:00)","fecha_de_conclusion":"04-03-2019 20:55:08 CET (ISO: 2019-03-04T20:55:08+01:00)","cantidad_reclamada":"10.119,90 €","lotes":"Sin lotes","anuncio_boe":"BOE-B-2019-5222","valor_subasta":"64.500,00 €","tasacion":"No consta","puja_minima":"Sin puja mínima","tramos_entre_pujas":"1.290,00 €","importe_del_deposito":"3.225,00 €"},"autoridad_gestora":{"codigo":"0824541004","descripcion":"JUZGADO 1ª INST E INSTRUCC. 4 (Ministerio de Justicia)","direccion":"PS SALZEREDA 15-18 21 ; 08921 SANTA COLOMA GRAMENET","telefono":"935515585","fax":"-","correo_electronico":"scpe.stacolomag@xij.gencat.cat"},"bienes":{"descripcion":"Vivienda sita en C. América nº 79, semisótano 2ª, de Santa Coloma de Gramanet.","idufir":"08105000054076","referencia_catastral":"3501810DF3930B0006DY","direccion":"C. América nº 79, semisótano 2ª","codigo_postal":"08924","localidad":"SANTA COLOMA DE GRAMENET","provincia":"Barcelona","vivienda_habitual":"Sí","situacion_posesoria":"Sin ocupantes","visitable":"No consta","inscripcion_registral":"Finca 27255 inscrita en el Registro de la Propiedad 1 de Santa Coloma de Gramanet en el Tomo 499, Libro 499, Folio 121. Inscripción de la hipoteca 7ª."},"relacionados":{"nombre":"NERETA INVEST, S.L.U.","nif":"B65967820","direccion":"RAMBLA CATALUNYA, 38, 8ª PLANTA","localidad":"08007 BARCELONA","provincia":"Barcelona","pais":"España"},"pujas":{"pujaMaxima":"33.540,00 €"}}