{"informacion_general":{"identificador":"SUB-JA-2017-63385","tipo_de_subasta":"JUDICIAL EN VIA DE APREMIO","fecha_de_inicio":"21-02-2020 18:00:00 CET (ISO: 2020-02-21T18:00:00+01:00)","fecha_de_conclusion":"12-03-2020 19:01:02 CET (ISO: 2020-03-12T19:01:02+01:00)","cantidad_reclamada":"44.746,60 €","lotes":"Sin lotes","anuncio_boe":"BOE-B-2020-7089","valor_subasta":"89.222,14 €","tasacion":"No consta","puja_minima":"Sin puja mínima","tramos_entre_pujas":"Sin tramos","importe_del_deposito":"4.461,11 €"},"autoridad_gestora":{"codigo":"4109142018","descripcion":"JUZGADO 1ª INSTANCIA 18 (Ministerio de Justicia)","direccion":"CL VERMONDO RESTA S/N S/N ; 41018 SEVILLA","telefono":"955043105","fax":"955043135","correo_electronico":"-"},"bienes":{"descripcion":"Registro de la Propiedad de Sevilla 9, al tomo 3.429, libro 463, folio 29, finca nº 4.826","direccion":"calle Ocho de Marzo nº 14 planta baja de Sevilla","codigo_postal":"41000","localidad":"SEVILLA","provincia":"Sevilla","situacion_posesoria":"No consta","visitable":"No consta"},"relacionados":{"nombre":"CAIXABANK S.A.","nif":"A08663619","direccion":"AVDA. DIAGONAL 621 BARCELONA","localidad":"08028 BARCELONA","provincia":"Barcelona"},"pujas":{"pujaMaxima":"50.000,00 €"}}