{"informacion_general":{"identificador":"SUB-NE-2018-325795","tipo_de_subasta":"NOTARIAL EN VENTA EXTRAJUDICIAL","fecha_de_inicio":"10-07-2018 18:00:00 CET (ISO: 2018-07-10T18:00:00+02:00)","fecha_de_conclusion":"30-07-2018 18:00:00 CET (ISO: 2018-07-30T18:00:00+02:00)","cantidad_reclamada":"92.944,35 €","lotes":"Sin lotes","anuncio_boe":"BOE-B-2018-36890","valor_subasta":"108.632,48 €","tasacion":"108.632,48 €","puja_minima":"Sin puja mínima","tramos_entre_pujas":"Sin tramos","importe_del_deposito":"5.431,62 €"},"autoridad_gestora":{"codigo":"9700200","descripcion":"Carlos Alejandro Vázquez Atkinson (ANCERT)","direccion":"Av. Martí Pujol, 121 ; 08912 Badalona","telefono":"933.847.725","fax":"-","correo_electronico":"cavazquez@correonotarial.org"},"bienes":{"descripcion":"VIVIENDA BAJO CUARTA, CALLE CANELONES, 1 BADALONA","direccion":"CALLE CANELONES, 1 BAJOS CUARTA","localidad":"Badalona","provincia":"Barcelona","situacion_posesoria":"No consta","visitable":"No consta"},"relacionados":{"nombre":"BANCO BILBAO ARGENTARIA, S.A.","nif":"A48265169","direccion":"PLAZA SAN NICOLAS, 4","localidad":"48005 Bilbao/Bilbo","provincia":"Vizcaya"},"pujas":{"pujaMaxima":null}}