{"informacion_general":{"identificador":"SUB-JA-2019-136297","tipo_de_subasta":"JUDICIAL EN VIA DE APREMIO","fecha_de_inicio":"18-10-2019 18:00:00 CET (ISO: 2019-10-18T18:00:00+02:00)","fecha_de_conclusion":"07-11-2019 18:00:00 CET (ISO: 2019-11-07T18:00:00+01:00)","cantidad_reclamada":"85.000,00 €","lotes":"Sin lotes","anuncio_boe":"BOE-B-2019-43445","valor_subasta":"154.800,00 €","tasacion":"154.800,00 €","puja_minima":"Sin puja mínima","tramos_entre_pujas":"3.096,00 €","importe_del_deposito":"7.740,00 €"},"autoridad_gestora":{"codigo":"3907542001","descripcion":"JUZGADO 1ª INSTANCIA 1 (Ministerio de Justicia)","direccion":"AV PEDRO SAN MARTIN s/n 13 ; 39071 SANTANDER","telefono":"942357018","fax":"942357019","correo_electronico":"juzgado.instancia1@justicia.cantabria.es"},"bienes":{"descripcion":"VIVIENDA EN C/ SANTA LUCIA, 67, 3º IZDA, DISTRIBUIDO EN COCINA, BAÑO, SALA Y TRES HABITACIONES","idufir":"39012000156238","referencia_catastral":"5630524VP3153B0009FE","direccion":"SANTA LUCIA, 67,3º IZDA","codigo_postal":"39003","localidad":"SANTANDER","provincia":"Cantabria","situacion_posesoria":"No consta","visitable":"No"},"relacionados":{"nombre":"LIBERBANK S.A.","nif":"A86201993","direccion":"CAMINO FUENTE DE LA MORA, 5","localidad":"28050 MADRID","provincia":"Madrid","pais":"España"},"pujas":{"pujaMaxima":"92.880,00 €"}}