{"informacion_general":{"identificador":"SUB-JA-2019-140988","tipo_de_subasta":"JUDICIAL EN VIA DE APREMIO","fecha_de_inicio":"18-12-2019 18:00:00 CET (ISO: 2019-12-18T18:00:00+01:00)","fecha_de_conclusion":"07-01-2020 20:27:26 CET (ISO: 2020-01-07T20:27:26+01:00)","cantidad_reclamada":"284.017,63 €","lotes":"4","forma_adjudicacion":"Separada para cada lote","anuncio_boe":"BOE-B-2019-53743","valor_subasta":"Ver valor de subasta en cada lote (los lotes se subastan de forma independiente)","tasacion":"Ver valor de tasación en cada lote (los lotes se subastan de forma independiente)","puja_minima":"Ver puja mínima de cada lote (adjudicación independiente)","tramos_entre_pujas":"Ver tramos de cada lote (adjudicación independiente)","importe_del_deposito":"Ver importe de consignación de cada lote (adjudicación independiente)"},"autoridad_gestora":{"codigo":"4109142021","descripcion":"JUZGADO 1ª INSTANCIA 21 (Ministerio de Justicia)","direccion":"CL VERMONDO RESTA S/N S/N ; 41018 SEVILLA","telefono":"955514038","fax":"955514038","correo_electronico":"4109142021@dgraj.cgob.junta-andalucia.es"},"lotes":{"1":{"valor_subasta":"22.154,13 €","importe_del_deposito":"1.107,70 €","puja_minima":"Sin puja mínima","tramos_entre_pujas":"443,08 €","descripcion":"aparcamiento nº 13 situado en planta sótano del edificio","idufir":"41048000651508","direccion":"C/ san jose 51","codigo_postal":"41300","localidad":"San José de La Rinconada","provincia":"Sevilla","situacion_posesoria":"No consta","visitable":"No consta"},"2":{"valor_subasta":"18.961,07 €","importe_del_deposito":"948,05 €","puja_minima":"Sin puja mínima","tramos_entre_pujas":"379,22 €","descripcion":"aparcamiento nº 15 situado en planta sótano del edificio","idufir":"41048000651522","direccion":"C/ San José 51","codigo_postal":"41300","localidad":"San José de La Rinconada","provincia":"Sevilla","situacion_posesoria":"No consta","visitable":"No consta"},"3":{"valor_subasta":"160.780,00 €","importe_del_deposito":"8.039,00 €","puja_minima":"Sin puja mínima","tramos_entre_pujas":"3.215,60 €","descripcion":"vivienda letra E en planta primera del edificio","idufir":"41048000651706","direccion":"C/ San José 51","codigo_postal":"41300","localidad":"San José de La Rinconada","provincia":"Sevilla","situacion_posesoria":"No consta","visitable":"No consta"},"4":{"valor_subasta":"178.860,00 €","importe_del_deposito":"8.943,00 €","puja_minima":"Sin puja mínima","tramos_entre_pujas":"3.577,20 €","descripcion":"vivienda letra F, en planta primera del edificio","idufir":"41048000651713","direccion":"C/ San José 51","codigo_postal":"41300","localidad":"San José de La rinconada","provincia":"Sevilla","situacion_posesoria":"No consta","visitable":"No consta"}},"relacionados":{},"pujas":{"1":"Sin puja","2":"Sin puja","3":"67.527,60 €","4":"Sin puja"}}