{"informacion_general":{"identificador":"SUB-JA-2018-92744","tipo_de_subasta":"JUDICIAL EN VIA DE APREMIO","fecha_de_inicio":"10-04-2018 18:00:00 CET (ISO: 2018-04-10T18:00:00+02:00)","fecha_de_conclusion":"30-04-2018 18:00:00 CET (ISO: 2018-04-30T18:00:00+02:00)","cantidad_reclamada":"130.175,41 €","lotes":"Sin lotes","anuncio_boe":"BOE-B-2018-20586","valor_subasta":"208.558,00 €","tasacion":"No consta","puja_minima":"Sin puja mínima","tramos_entre_pujas":"Sin tramos","importe_del_deposito":"10.427,90 €"},"autoridad_gestora":{"codigo":"3800642005","descripcion":"JUZGADO 1ª INSTANCIA 5 (Ministerio de Justicia)","direccion":"AV CHAYOFITA S/N S/N ; 38650 PLAYA DE LOS CRISTIANOS","telefono":"922777631","fax":"922747330","correo_electronico":"-"},"bienes":{"descripcion":"APARTAMENTO en planta segunda del edificio \"Sunflower II\", Cueva del Polvo, Natero del Muchacho","idufir":"38002000224076","referencia_catastral":"9640901CS1293N0047DA","direccion":"Trv Apostol Santiago Segu nº1, Planta 2ª, puerta 46, Sunflower II, Playa de la Arena","codigo_postal":"38680","localidad":"Santiago del Teide","provincia":"Santa Cruz de Tenerife","situacion_posesoria":"No consta","visitable":"No consta","inscripcion_registral":"FINCA 7911 de Santiago del Teide, AL tomo 881, libro 171, Folio 185 APARECE LA inscripción 10ª, última de dominio."},"relacionados":{"nombre":"BANCO SABADELL S.A.","nif":"A08000143","direccion":"plaça de Sant Roc, nº20","localidad":"08201 BARCELONA","provincia":"Barcelona"},"pujas":{"pujaMaxima":"145.990,60 €"}}