{"informacion_general":{"identificador":"SUB-JV-2019-138989","tipo_de_subasta":"JUDICIAL VOLUNTARIA","fecha_de_inicio":"28-11-2019 18:00:00 CET (ISO: 2019-11-28T18:00:00+01:00)","fecha_de_conclusion":"18-12-2019 18:10:51 CET (ISO: 2019-12-18T18:10:51+01:00)","cantidad_reclamada":"0,00 €","lotes":"Sin lotes","anuncio_boe":"BOE-B-2019-50735","valor_subasta":"265.114,30 €","tasacion":"No consta","puja_minima":"Sin puja mínima","tramos_entre_pujas":"5.302,29 €","importe_del_deposito":"13.255,72 €"},"autoridad_gestora":{"codigo":"0812142008","descripcion":"JUZGADO 1ª INSTANCIA 8 (Ministerio de Justicia)","direccion":"CL ALCALDE ABRIL 24 24 ; 08302 MATARO","telefono":"936931070","fax":"936931071","correo_electronico":"instancia8.mataro@xij.gencat.cat"},"bienes":{"descripcion":"Vivienda dúplex en un edificio plurifamiliar aislado sita en C/ Valencia nº 55 de la Urbanización Meya en la localidad de Alella.","referencia_catastral":"2436004DF4923N0006PS","direccion":"calle valencia 55, urbanización Meya","codigo_postal":"08348","localidad":"alella","provincia":"Barcelona","situacion_posesoria":"No consta","visitable":"No consta"},"relacionados":{},"pujas":{"pujaMaxima":"143.161,83 €"}}