{"informacion_general":{"identificador":"SUB-JA-2019-125804","tipo_de_subasta":"JUDICIAL EN VIA DE APREMIO","fecha_de_inicio":"28-05-2019 18:00:00 CET (ISO: 2019-05-28T18:00:00+02:00)","fecha_de_conclusion":"18-06-2019 01:37:05 CET (ISO: 2019-06-18T01:37:05+02:00)","cantidad_reclamada":"54.940,06 €","lotes":"Sin lotes","anuncio_boe":"BOE-B-2019-22630","valor_subasta":"108.405,00 €","tasacion":"No consta","puja_minima":"Sin puja mínima","tramos_entre_pujas":"2.168,10 €","importe_del_deposito":"5.420,25 €"},"autoridad_gestora":{"codigo":"0401342001","descripcion":"JUZGADO 1ª INSTANCIA 1 (Ministerio de Justicia)","direccion":"CR DE RONDA 120 120 ; 04006 ALMERIA","telefono":"950809073","fax":"950204214","correo_electronico":"jinstancia.1.almeria.jus@juntadeandalucia.es"},"bienes":{"descripcion":"APARTAMENTO PLANTA BAJA DE 57,75 M2 UTILES","direccion":"CALLE CURRY S/N","codigo_postal":"04006","localidad":"SAN JOSE","provincia":"Almería","vivienda_habitual":"No","situacion_posesoria":"No consta","visitable":"No consta"},"relacionados":{"nombre":"CAJAMAR CAJA RURAL S.C.C.","nif":"F04743175","direccion":"C/ CURRY S/N","localidad":"04118 ALMERIA","provincia":"Almería","pais":"España"},"pujas":{"pujaMaxima":"93.228,30 €"}}