{"informacion_general":{"identificador":"SUB-JA-2019-139821","tipo_de_subasta":"JUDICIAL EN VIA DE APREMIO","fecha_de_inicio":"18-02-2020 18:00:00 CET (ISO: 2020-02-18T18:00:00+01:00)","fecha_de_conclusion":"09-03-2020 18:00:00 CET (ISO: 2020-03-09T18:00:00+01:00)","cantidad_reclamada":"50.225,68 €","lotes":"Sin lotes","anuncio_boe":"BOE-B-2020-6412","valor_subasta":"102.754,27 €","tasacion":"No consta","puja_minima":"Sin puja mínima","tramos_entre_pujas":"2.055,08 €","importe_del_deposito":"5.137,71 €"},"autoridad_gestora":{"codigo":"0490241002","descripcion":"JUZGADO 1ª INST E INSTRUCC. 2 (Ministerio de Justicia)","direccion":"CL OCEANO ATLANTICO 8 8 ; 04700 EJIDO(EL)","telefono":"950578023","fax":"950578025","correo_electronico":"JMixto.2.Ejido.JUS@juntadeandalucia.es"},"bienes":{"descripcion":"VIVIENDA EN BALERMA","direccion":"C/PRINCESA SOFIA 2 B","codigo_postal":"04712","localidad":"BALERMA","provincia":"Almería","situacion_posesoria":"No consta","visitable":"No consta","inscripcion_registral":"FINCA REGISTRAL Nº 93061, inscrita al folio 158, tomo 2543, libro 1452 del Registro de la Propiedad nº 2 de El Ejido."},"relacionados":{},"pujas":{"pujaMaxima":null}}