{"informacion_general":{"identificador":"SUB-JA-2016-22983","tipo_de_subasta":"JUDICIAL EN VIA DE APREMIO","fecha_de_inicio":"04-11-2016 18:00:00 CET (ISO: 2016-11-04T18:00:00+01:00)","fecha_de_conclusion":"24-11-2016 18:00:00 CET (ISO: 2016-11-24T18:00:00+01:00)","cantidad_reclamada":"259.242,92 €","lotes":"2","forma_adjudicacion":"Conjunta para todos los lotes","anuncio_boe":"BOE-B-2016-53539","valor_subasta":"434.741,55 €","tasacion":"No consta","puja_minima":"Sin puja mínima","tramos_entre_pujas":"Sin tramos","importe_del_deposito":"21.737,08 €"},"autoridad_gestora":{"codigo":"0301442001","descripcion":"JUZGADO 1ª INSTANCIA 1 (Ministerio de Justicia)","direccion":"AV AGUILERA 53 53 ; 03007 ALICANTE","telefono":"965935729","fax":"965935848","correo_electronico":"-"},"lotes":{"1":{"descripcion":"VIVIENDA EN ALICANTE, CALLE PINTOR LORENZO CASANOVA Nº 34-36, ÁTICO.","referencia_catastral":"9369617YH1496G0012QP","direccion":"C/ PINTOR LORENZO CASANOVA Nº 34-36","codigo_postal":"03003","localidad":"ALICANTE","provincia":"Alicante","situacion_posesoria":"No consta","visitable":"No","cargas":"VER ANEXO"},"2":{"descripcion":"PLAZA DE GARAJE CON TRASTERO NUMERADOS CON EL NUMERO 3. SITO EN ALICANTE, CALLE PINTOR LORENZO CASANOVA Nº 34-36","referencia_catastral":"9369617YH1496G0015RD","direccion":"CALLE PINTOR LORENZO CASANOVA","codigo_postal":"03003","localidad":"ALICANTE","provincia":"Alicante","vivienda_habitual":"No","situacion_posesoria":"No consta","visitable":"No","cargas":"VER ANEXO"}},"relacionados":{"nombre":"BANKINTER S.A.","nif":"A28157360","direccion":"PASEO DE LA CASTELLANA Nº 29","localidad":"28046 MADRID","provincia":"Madrid"},"pujas":{}}