{"informacion_general":{"identificador":"SUB-JV-2019-129647","tipo_de_subasta":"JUDICIAL VOLUNTARIA","fecha_de_inicio":"16-07-2019 18:00:00 CET (ISO: 2019-07-16T18:00:00+02:00)","fecha_de_conclusion":"05-08-2019 18:00:00 CET (ISO: 2019-08-05T18:00:00+02:00)","cantidad_reclamada":"0,00 €","lotes":"Sin lotes","anuncio_boe":"BOE-B-2019-31453","valor_subasta":"89.681,22 €","tasacion":"89.681,22 €","puja_minima":"Sin puja mínima","tramos_entre_pujas":"Sin tramos","importe_del_deposito":"4.484,06 €"},"autoridad_gestora":{"codigo":"1913042006","descripcion":"JUZGADO 1ª INSTANCIA 6 (Ministerio de Justicia)","direccion":"PZ FERNANDO BELADIEZ S/N S/N ; 19071 GUADALAJARA","telefono":"949209966","fax":"949209972","correo_electronico":"instancia6.guadalajara@justicia.es"},"bienes":{"descripcion":"la vivienda unifamiliar pareada sita en Alovera (Guadalajara), C/ Federico García Lorca nº 44, inscrita en el Registro de la Propiedad nº 3 de Guadalajara, inscripción sexta, folio 76 del Libro 57, Tomo 1677, finca 5205.","direccion":"calle Federico Garcia Lorca 44","codigo_postal":"19208","localidad":"Alovera","provincia":"Guadalajara","situacion_posesoria":"No consta","visitable":"No consta","cargas":"ver certificacion","inscripcion_registral":"Registro de la Propiedad nº 3 de Guadalajara, inscripción sexta, folio 76 del Libro 57, Tomo 1677, finca 5205"},"relacionados":{},"pujas":{"pujaMaxima":"90.000,00 €"}}